onego/__init__.py
onego/files/__init__.py
onego/killable_thread/__init__.py
onego/logger/__init__.py
onego/sessions/__init__.py
onego/sessions/chrome.py
onego/sessions/get_chrome_version.py
onego/utils/__init__.py
onego-1.1.5.dist-info/LICENSE
onego-1.1.5.dist-info/METADATA
onego-1.1.5.dist-info/WHEEL
onego-1.1.5.dist-info/top_level.txt
onego-1.1.5.dist-info/RECORD
